openfaker/__init__.py
openfaker/bot.py
openfaker/exceptions.py
openfaker/openfaker.py
openfaker/prompter.py
openfaker/utils.py
openfaker-0.0.1.dist-info/LICENSE
openfaker-0.0.1.dist-info/METADATA
openfaker-0.0.1.dist-info/WHEEL
openfaker-0.0.1.dist-info/top_level.txt
openfaker-0.0.1.dist-info/RECORD
