Metadata-Version: 2.1
Name: openfaker
Version: 0.0.1
Summary: Generate fake data with OpenAI's GPT-3 API.
Home-page: https://github.com/zh-plus/faker-openai
Author: Hao Zheng
Author-email: zhenghaosustc@gmail.com
License: MIT
Keywords: openai-gpt3,fake-data,data generation
Classifier: Programming Language :: Python :: 3
Classifier: Intended Audience :: Developers
Classifier: Topic :: Scientific/Engineering
Classifier: License :: OSI Approved :: MIT License
Classifier: Programming Language :: Python :: 3.11
Classifier: Operating System :: OS Independent
License-File: LICENSE
Requires-Dist: openai
Requires-Dist: pycountry
